ragstack_mcp/__init__.py
ragstack_mcp/server.py
ragstack_mcp-0.1.2.dev9.dist-info/METADATA
ragstack_mcp-0.1.2.dev9.dist-info/WHEEL
ragstack_mcp-0.1.2.dev9.dist-info/entry_points.txt
ragstack_mcp-0.1.2.dev9.dist-info/RECORD
