Metadata-Version: 2.4
Name: ragstack-mcp
Version: 0.1.2.dev9
Summary: MCP server for RAGStack knowledge base - search, chat, upload, and scrape
Project-URL: Homepage, https://github.com/HatmanStack/RAGStack-Lambda
Project-URL: Repository, https://github.com/HatmanStack/RAGStack-Lambda
Author: RAGStack Team
License-Expression: MIT
Keywords: ai,bedrock,knowledge-base,mcp,rag
Classifier: Development Status :: 4 - Beta
Classifier: Intended Audience :: Developers
Classifier: License :: OSI Approved :: MIT License
Classifier: Programming Language :: Python :: 3
Classifier: Programming Language :: Python :: 3.10
Classifier: Programming Language :: Python :: 3.11
Classifier: Programming Language :: Python :: 3.12
Classifier: Programming Language :: Python :: 3.13
Requires-Python: >=3.10
Requires-Dist: httpx>=0.27.0
Requires-Dist: mcp>=1.0.0
